btog.v
module btog (
    input [3:0]a,output [3:0]b
);
assign b[3]=a[3];
assign b[2]=a[3]^a[2];
assign b[1]=a[2]^a[1];
assign b[0]=a[1]^a[0];
endmodule

btog_tb.v
module btog_tb;
reg [3:0]a;
wire [3:0]b;

btog uut(.a(a),.b(b));
initial begin
    $dumpfile("btog.vcd");
    $dumpvars(0,btog_tb);
    //$monitor("time=%0t | a=%b b=%b",&$time,&a ,&b);
    a=4'b0000;
    #10;
    a=4'b0001;#10;
    a=4'b0010;#10;
    a=4'b0011;#10;
    a=4'b0100;#10;
    a=4'b0101;#10;
    a=4'b0101;#10;
    a=4'b0110;#10;
    a=4'b0111;#10;
    a=4'b1000;#10;
    a=4'b1001;#10;
    a=4'b1010;#10;
    a=4'b1011;#10;
    a=4'b1100;#10;
    a=4'b1101;#10;
    a=4'b1110;#10;
    a=4'b1111;#10;

end
    
endmodule

btog.vcd
$date
	Tue Aug 05 10:35:24 2025
$end
$version
	Icarus Verilog
$end
$timescale
	1s
$end
$scope module btog_tb $end
$var wire 4 ! b [3:0] $end
$var reg 4 " a [3:0] $end
$scope module uut $end
$var wire 4 # a [3:0] $end
$var wire 4 $ b [3:0] $end
$upscope $end
$upscope $end
$enddefinitions $end
$comment Show the parameter values. $end
$dumpall
$end
#0
$dumpvars
b0 $
b0 #
b0 "
b0 !
$end
#10
b1 !
b1 $
b1 "
b1 #
#20
b11 !
b11 $
b10 "
b10 #
#30
b10 !
b10 $
b11 "
b11 #
#40
b110 !
b110 $
b100 "
b100 #
#50
b111 !
b111 $
b101 "
b101 #
#70
b101 !
b101 $
b110 "
b110 #
#80
b100 !
b100 $
b111 "
b111 #
#90
b1100 !
b1100 $
b1000 "
b1000 #
#100
b1101 !
b1101 $
b1001 "
b1001 #
#110
b1111 !
b1111 $
b1010 "
b1010 #
#120
b1110 !
b1110 $
b1011 "
b1011 #
#130
b1010 !
b1010 $
b1100 "
b1100 #
#140
b1011 !
b1011 $
b1101 "
b1101 #
#150
b1001 !
b1001 $
b1110 "
b1110 #
#160
b1000 !
b1000 $
b1111 "
b1111 #
